mmdit/__init__.py
mmdit/attention.py
mmdit/block.py
mmdit_pytorch-0.2.6.dist-info/LICENSE
mmdit_pytorch-0.2.6.dist-info/METADATA
mmdit_pytorch-0.2.6.dist-info/WHEEL
mmdit_pytorch-0.2.6.dist-info/RECORD
