Metadata-Version: 2.1
Name: mmdit-pytorch
Version: 0.2.6
Summary: A standalone implementation of a single block of Multimodal Diffusion Transformer (MMDiT) originally proposed in Scaling Rectified Flow Transformers for High-Resolution Image Synthesis (https://arxiv.org/abs/2403.03206) in PyTorch with minimal dependencies.
Home-page: https://github.com/KennyStryker/mmdit-pytorch.git
License: MIT
Author: Kenny Stryker
Author-email: nggkenny@gmail.com
Requires-Python: >=3.12
Classifier: Development Status :: 4 - Beta
Classifier: Intended Audience :: Science/Research
Classifier: License :: OSI Approved :: MIT License
Classifier: Natural Language :: English
Classifier: Operating System :: OS Independent
Classifier: Programming Language :: Python :: 3
Classifier: Programming Language :: Python :: 3.12
Classifier: Programming Language :: Python :: 3.13
Classifier: Topic :: Scientific/Engineering :: Artificial Intelligence
Classifier: Topic :: Software Development :: Libraries
Classifier: Typing :: Typed
Requires-Dist: einops (>=0.8.1,<0.9.0)
Requires-Dist: numpy (>=2.2.4,<3.0.0)
Requires-Dist: torch (>=2.6.0,<3.0.0)
Project-URL: Repository, https://github.com/KennyStryker/mmdit-pytorch.git
